cosmolib/__init__.py
cosmolib/data/__init__.py
cosmolib/data/photo.py
cosmolib/data/spectro.py
cosmolib/plot/__init__.py
cosmolib-0.4.dist-info/METADATA
cosmolib-0.4.dist-info/WHEEL
cosmolib-0.4.dist-info/licenses/LICENSE
cosmolib-0.4.dist-info/RECORD
