Metadata-Version: 2.4
Name: cosmolib
Version: 0.4
Summary: Easy-to-use formats and plots for cosmological observables
Project-URL: Repository, https://github.com/astro-ph/cosmolib
Project-URL: Issues, https://github.com/astro-ph/cosmolib/issues
Author-email: Nicolas Tessore <n.tessore@ucl.ac.uk>, Guadalupe Canas-Herrera <canasherrera@strw.leidenuniv.nl>
Maintainer-email: Nicolas Tessore <n.tessore@ucl.ac.uk>, Guadalupe Canas-Herrera <canasherrera@strw.leidenuniv.nl>
License-Expression: MIT
License-File: LICENSE
Classifier: License :: OSI Approved :: MIT License
Classifier: Operating System :: OS Independent
Classifier: Programming Language :: Python :: 3
Requires-Python: >=3.9
Requires-Dist: numpy
Provides-Extra: test
Requires-Dist: pytest>=6.0; extra == 'test'
